code_data/.gitignore
code_data/__init__.py
code_data/_args.py
code_data/_blocks.py
code_data/_cli.py
code_data/_code_data.py
code_data/_constants.py
code_data/_flags_data.py
code_data/_flags_data_test.py
code_data/_json_data.py
code_data/_line_mapping.py
code_data/_line_mapping_test.py
code_data/_normalize.py
code_data/_test.py
code_data/_test_cli.py
code_data/_test_modules.py
code_data/_test_verify_code.py
code_data/dataclass_hide_default.py
code_data/module_codes.py
code_data/_test_minimized/README.md
code_data/_test_minimized/appnope._dummy.py
code_data/_test_minimized/astroid.brain.brain_numpy_ndarray.py
code_data/_test_minimized/asyncore.py
code_data/_test_minimized/bytecode.tests.long_lines_example.py
code_data/_test_minimized/ensurepip.__main__.py
code_data/_test_minimized/flit_core.vendor.tomli._types.py
code_data/_test_minimized/generated_example.py
code_data/_test_minimized/gitdb.const.py
code_data/_test_minimized/hypothesis.internal.floats.py
code_data/_test_minimized/identify.interpreters.py
code_data/_test_minimized/idlelib.idle_test.test_hyperparser.py
code_data/_test_minimized/ipykernel.tests.test_message_spec.py
code_data/_test_minimized/jedi.plugins.py
code_data/_test_minimized/json.scanner.py
code_data/_test_minimized/lib2to3.fixes.fix_itertools_imports.py
code_data/_test_minimized/libcst.tests.test_tabs.py
code_data/_test_minimized/notebook.tests.test_config_manager.py
code_data/_test_minimized/numpy.core.tests.test_multiarray.py
code_data/_test_minimized/pip._vendor.pep517.build.py
code_data/_test_minimized/pip._vendor.rich.color.py
code_data/_test_minimized/pip._vendor.rich.pretty.py
code_data/_test_minimized/pre_commit.languages.r.py
code_data/_test_minimized/prompt_toolkit.styles.named_colors.py
code_data/_test_minimized/pygments.formatters.irc.py
code_data/_test_minimized/rich._emoji_codes.py
code_data/_test_minimized/setuptools._vendor.more_itertools.more.py
code_data/_test_minimized/setuptools.config.py
code_data-1.0.1.dist-info/entry_points.txt
code_data-1.0.1.dist-info/LICENSE
code_data-1.0.1.dist-info/WHEEL
code_data-1.0.1.dist-info/METADATA
code_data-1.0.1.dist-info/RECORD
